LICENSE
MANIFEST.in
README.md
pyproject.toml
setup.py
src/main/__init__.py
src/main/bootstrap.py
src/main/cmd.py
src/playbook/bootstrap.yaml
src/playbook/roles/agent/tasks/main.yaml
src/playbook/roles/controller/tasks/main.yaml
src/playbook/roles/meta/main.yaml
src/playbook/roles/minio/tasks/main.yaml
src/playbook/roles/mysql/tasks/main.yaml
src/test_bootstrap.egg-info/PKG-INFO
src/test_bootstrap.egg-info/SOURCES.txt
src/test_bootstrap.egg-info/dependency_links.txt
src/test_bootstrap.egg-info/entry_points.txt
src/test_bootstrap.egg-info/requires.txt
src/test_bootstrap.egg-info/top_level.txt