Metadata-Version: 2.1
Name: test-bootstrap
Version: 0.0.1
Author: sw
Author-email: 15031259256@163.com
Classifier: Programming Language :: Python :: 3
Classifier: License :: Free for non-commercial use
Classifier: Operating System :: OS Independent
License-File: LICENSE
